randomvalue/__init__.py
randomvalue/randomvalue.py
randomvalue-111.dist-info/METADATA
randomvalue-111.dist-info/WHEEL
randomvalue-111.dist-info/top_level.txt
randomvalue-111.dist-info/RECORD
